glap/__init__.py
glap/cli.py
glap-0.3.1.dist-info/entry_points.txt
glap-0.3.1.dist-info/LICENSE
glap-0.3.1.dist-info/WHEEL
glap-0.3.1.dist-info/METADATA
glap-0.3.1.dist-info/RECORD
