Metadata-Version: 2.1
Name: glap
Version: 0.3.1
Summary: GitLab Artifact Puller / Downloader
Home-page: https://github.com/Mountlex/glap
License: MIT
Author: Alexander Lindermayr
Author-email: alexander.lindermayr97@gmail.com
Requires-Python: >=3.7,<4.0
Classifier: License :: OSI Approved :: MIT License
Classifier: Programming Language :: Python :: 3
Classifier: Programming Language :: Python :: 3.7
Classifier: Programming Language :: Python :: 3.8
Classifier: Programming Language :: Python :: 3.9
Requires-Dist: appdirs (>=1.4.4,<2.0.0)
Requires-Dist: click (>=7.1.2,<8.0.0)
Requires-Dist: python-gitlab (>=2.6.0,<3.0.0)
Requires-Dist: requests (>=2.25.1,<3.0.0)
Requires-Dist: toml (>=0.10.2,<0.11.0)
Requires-Dist: yaspin (>=1.4.0,<2.0.0)
Project-URL: Repository, https://github.com/Mountlex/glap
